eia.py
codejail_includes-2.0.0.dist-info/licenses/LICENSE
loncapa/__init__.py
loncapa/loncapa_check.py
verifiers/__init__.py
verifiers/draganddrop.py
verifiers/tests_draganddrop.py
codejail_includes-2.0.0.dist-info/METADATA
codejail_includes-2.0.0.dist-info/WHEEL
codejail_includes-2.0.0.dist-info/top_level.txt
codejail_includes-2.0.0.dist-info/RECORD
